{
  "metadata": {
    "eventKey": 96489,
    "pen": 3,
    "careerEventId": 1,
    "scheduleKey": 56250,
    "accessCode": 850523,
    "eventName": "Coast and Roast Crit - TPV Career Mode Stage 1",
    "completedAt": "2026-01-09T09:44:00.258Z",
    "raceDate": "2026-01-09T09:44:00.258Z",
    "fetchedAt": "2026-01-09T09:50:13.501Z",
    "source": "api",
    "processedAt": "2026-01-09T09:50:42.197Z"
  },
  "results": [
    {
      "position": 1,
      "time": 2164738,
      "avgPower": 239,
      "maxPower": 807,
      "nrmPower": 255,
      "firstName": "Milán",
      "lastName": "Németh",
      "teamName": "",
      "distance": 23541109,
      "delta": 0,
      "deltaTime": 0,
      "deltaDistance": 0,
      "points": 0,
      "arr": 1076,
      "rating": 1073,
      "pen": 3,
      "gender": "2",
      "ageBand": "",
      "ngb": "",
      "ngbID": "",
      "uciID": "",
      "playerId": "Bot1967",
      "country": "hun",
      "isDNF": false,
      "isBot": true,
      "avgHr": 144,
      "maxHr": 167
    },
    {
      "position": 2,
      "time": 2164954,
      "avgPower": 233,
      "maxPower": 1325,
      "nrmPower": 244,
      "firstName": "Sten",
      "lastName": "Michaelsen",
      "teamName": "",
      "distance": 23541109,
      "delta": 216,
      "deltaTime": 216,
      "deltaDistance": 0,
      "points": 0,
      "arr": 1073,
      "rating": 1064,
      "pen": 3,
      "gender": "2",
      "ageBand": "",
      "ngb": "",
      "ngbID": "",
      "uciID": "",
      "playerId": "Bot4499",
      "country": "den",
      "isDNF": false,
      "isBot": true,
      "avgHr": 163,
      "maxHr": 192
    },
    {
      "position": 3,
      "time": 2165031,
      "avgPower": 248,
      "maxPower": 898,
      "nrmPower": 260,
      "firstName": "Dobroslav",
      "lastName": "Košarac",
      "teamName": "Meisterkuhl",
      "distance": 23541109,
      "delta": 293,
      "deltaTime": 293,
      "deltaDistance": 0,
      "points": 0,
      "arr": 906,
      "rating": 920,
      "pen": 3,
      "gender": "2",
      "ageBand": "",
      "ngb": "",
      "ngbID": "",
      "uciID": "",
      "playerId": "Bot5922",
      "country": "cze",
      "isDNF": false,
      "isBot": true,
      "avgHr": 175,
      "maxHr": 204
    },
    {
      "position": 4,
      "time": 2165296,
      "avgPower": 232,
      "maxPower": 705,
      "nrmPower": 243,
      "firstName": "Frances",
      "lastName": "Peters",
      "teamName": "AMO Solutions",
      "distance": 23541109,
      "delta": 558,
      "deltaTime": 558,
      "deltaDistance": 0,
      "points": 0,
      "arr": 879,
      "rating": 882,
      "pen": 3,
      "gender": "2",
      "ageBand": "",
      "ngb": "",
      "ngbID": "",
      "uciID": "",
      "playerId": "Bot839",
      "country": "rsa",
      "isDNF": false,
      "isBot": true,
      "avgHr": 162,
      "maxHr": 186
    },
    {
      "position": 5,
      "time": 2168044,
      "avgPower": 243,
      "maxPower": 722,
      "nrmPower": 250,
      "firstName": "Erik",
      "lastName": "Sund",
      "teamName": "Coalition",
      "distance": 23541109,
      "delta": 3306,
      "deltaTime": 3306,
      "deltaDistance": 0,
      "points": 0,
      "arr": 794,
      "rating": 854,
      "pen": 3,
      "gender": "0",
      "ageBand": "40-44",
      "ngb": "",
      "ngbID": "",
      "uciID": "",
      "playerId": "E930EA1B86BB8DD2",
      "country": "swe",
      "isDNF": false,
      "isBot": false,
      "avgHr": 156,
      "maxHr": 176
    },
    {
      "position": 6,
      "time": 2168471,
      "avgPower": 215,
      "maxPower": 386,
      "nrmPower": 222,
      "firstName": "Marianne",
      "lastName": "Bates",
      "teamName": "",
      "distance": 23541109,
      "delta": 3733,
      "deltaTime": 3733,
      "deltaDistance": 0,
      "points": 0,
      "arr": 865,
      "rating": 850,
      "pen": 3,
      "gender": "2",
      "ageBand": "",
      "ngb": "",
      "ngbID": "",
      "uciID": "",
      "playerId": "Bot9883",
      "country": "gbr",
      "isDNF": false,
      "isBot": true,
      "avgHr": 181,
      "maxHr": 198
    },
    {
      "position": 7,
      "time": 2168777,
      "avgPower": 213,
      "maxPower": 323,
      "nrmPower": 218,
      "firstName": "Ellen",
      "lastName": "Kramer",
      "teamName": "Sherpa",
      "distance": 23541109,
      "delta": 4038,
      "deltaTime": 4038,
      "deltaDistance": 0,
      "points": 0,
      "arr": 948,
      "rating": 918,
      "pen": 3,
      "gender": "2",
      "ageBand": "",
      "ngb": "",
      "ngbID": "",
      "uciID": "",
      "playerId": "Bot5520",
      "country": "ned",
      "isDNF": false,
      "isBot": true,
      "avgHr": 191,
      "maxHr": 205
    },
    {
      "position": 8,
      "time": 2168820,
      "avgPower": 306,
      "maxPower": 468,
      "nrmPower": 316,
      "firstName": "Callum",
      "lastName": "Taylor",
      "teamName": "",
      "distance": 23541109,
      "delta": 4082,
      "deltaTime": 4082,
      "deltaDistance": 0,
      "points": 0,
      "arr": 768,
      "rating": 789,
      "pen": 3,
      "gender": "2",
      "ageBand": "",
      "ngb": "",
      "ngbID": "",
      "uciID": "",
      "playerId": "Bot6174",
      "country": "irl",
      "isDNF": false,
      "isBot": true,
      "avgHr": 183,
      "maxHr": 194
    },
    {
      "position": 9,
      "time": 2168856,
      "avgPower": 216,
      "maxPower": 389,
      "nrmPower": 222,
      "firstName": "Corina",
      "lastName": "Yang",
      "teamName": "Delta",
      "distance": 23541109,
      "delta": 4118,
      "deltaTime": 4118,
      "deltaDistance": 0,
      "points": 0,
      "arr": 774,
      "rating": 756,
      "pen": 3,
      "gender": "2",
      "ageBand": "",
      "ngb": "",
      "ngbID": "",
      "uciID": "",
      "playerId": "Bot9821",
      "country": "usa",
      "isDNF": false,
      "isBot": true,
      "avgHr": 164,
      "maxHr": 178
    },
    {
      "position": 10,
      "time": 2169045,
      "avgPower": 239,
      "maxPower": 367,
      "nrmPower": 244,
      "firstName": "Polly",
      "lastName": "Matthews",
      "teamName": "Systech",
      "distance": 23541109,
      "delta": 4306,
      "deltaTime": 4306,
      "deltaDistance": 0,
      "points": 0,
      "arr": 881,
      "rating": 870,
      "pen": 3,
      "gender": "2",
      "ageBand": "",
      "ngb": "",
      "ngbID": "",
      "uciID": "",
      "playerId": "Bot3404",
      "country": "nzl",
      "isDNF": false,
      "isBot": true,
      "avgHr": 162,
      "maxHr": 173
    },
    {
      "position": 11,
      "time": 2169213,
      "avgPower": 268,
      "maxPower": 416,
      "nrmPower": 279,
      "firstName": "Karell",
      "lastName": "Hodge",
      "teamName": "Dashix",
      "distance": 23541109,
      "delta": 4474,
      "deltaTime": 4474,
      "deltaDistance": 0,
      "points": 0,
      "arr": 758,
      "rating": 780,
      "pen": 3,
      "gender": "2",
      "ageBand": "",
      "ngb": "",
      "ngbID": "",
      "uciID": "",
      "playerId": "Bot6311",
      "country": "aia",
      "isDNF": false,
      "isBot": true,
      "avgHr": 158,
      "maxHr": 170
    },
    {
      "position": 12,
      "time": 2169441,
      "avgPower": 267,
      "maxPower": 485,
      "nrmPower": 277,
      "firstName": "Levi",
      "lastName": "Scott",
      "teamName": "",
      "distance": 23541109,
      "delta": 4703,
      "deltaTime": 4703,
      "deltaDistance": 0,
      "points": 0,
      "arr": 776,
      "rating": 795,
      "pen": 3,
      "gender": "2",
      "ageBand": "",
      "ngb": "",
      "ngbID": "",
      "uciID": "",
      "playerId": "Bot1665",
      "country": "gbr",
      "isDNF": false,
      "isBot": true,
      "avgHr": 162,
      "maxHr": 175
    },
    {
      "position": 13,
      "time": 2169649,
      "avgPower": 209,
      "maxPower": 376,
      "nrmPower": 215,
      "firstName": "Shirley",
      "lastName": "Ruiz",
      "teamName": "",
      "distance": 23541109,
      "delta": 4911,
      "deltaTime": 4911,
      "deltaDistance": 0,
      "points": 0,
      "arr": 794,
      "rating": 795,
      "pen": 3,
      "gender": "2",
      "ageBand": "",
      "ngb": "",
      "ngbID": "",
      "uciID": "",
      "playerId": "Bot8371",
      "country": "aru",
      "isDNF": false,
      "isBot": true,
      "avgHr": 180,
      "maxHr": 196
    },
    {
      "position": 14,
      "time": 2178944,
      "avgPower": 255,
      "maxPower": 400,
      "nrmPower": 265,
      "firstName": "Ronald",
      "lastName": "Bacchus",
      "teamName": "eVOX",
      "distance": 23541109,
      "delta": 14206,
      "deltaTime": 14206,
      "deltaDistance": 0,
      "points": 0,
      "arr": 734,
      "rating": 750,
      "pen": 3,
      "gender": "2",
      "ageBand": "",
      "ngb": "",
      "ngbID": "",
      "uciID": "",
      "playerId": "Bot9705",
      "country": "guy",
      "isDNF": false,
      "isBot": true,
      "avgHr": 186,
      "maxHr": 201
    },
    {
      "position": 15,
      "time": 2179182,
      "avgPower": 286,
      "maxPower": 533,
      "nrmPower": 298,
      "firstName": "Francisco",
      "lastName": "Luna",
      "teamName": "Nitro",
      "distance": 23541109,
      "delta": 14443,
      "deltaTime": 14443,
      "deltaDistance": 0,
      "points": 0,
      "arr": 599,
      "rating": 627,
      "pen": 3,
      "gender": "2",
      "ageBand": "",
      "ngb": "",
      "ngbID": "",
      "uciID": "",
      "playerId": "Bot9037",
      "country": "mex",
      "isDNF": false,
      "isBot": true,
      "avgHr": 184,
      "maxHr": 202
    },
    {
      "position": 16,
      "time": 2183333,
      "avgPower": 218,
      "maxPower": 339,
      "nrmPower": 224,
      "firstName": "Evelyn",
      "lastName": "Smith",
      "teamName": "",
      "distance": 23541109,
      "delta": 18595,
      "deltaTime": 18595,
      "deltaDistance": 0,
      "points": 0,
      "arr": 851,
      "rating": 843,
      "pen": 3,
      "gender": "2",
      "ageBand": "",
      "ngb": "",
      "ngbID": "",
      "uciID": "",
      "playerId": "Bot6586",
      "country": "wal",
      "isDNF": false,
      "isBot": true,
      "avgHr": 169,
      "maxHr": 182
    },
    {
      "position": 17,
      "time": 2183608,
      "avgPower": 209,
      "maxPower": 318,
      "nrmPower": 216,
      "firstName": "Bianca",
      "lastName": "Kramer",
      "teamName": "Aspire",
      "distance": 23541109,
      "delta": 18870,
      "deltaTime": 18870,
      "deltaDistance": 0,
      "points": 0,
      "arr": 883,
      "rating": 861,
      "pen": 3,
      "gender": "2",
      "ageBand": "",
      "ngb": "",
      "ngbID": "",
      "uciID": "",
      "playerId": "Bot4229",
      "country": "ned",
      "isDNF": false,
      "isBot": true,
      "avgHr": 174,
      "maxHr": 186
    },
    {
      "position": 18,
      "time": 2185475,
      "avgPower": 216,
      "maxPower": 1165,
      "nrmPower": 225,
      "firstName": "Alexander",
      "lastName": "Smet",
      "teamName": "",
      "distance": 23541109,
      "delta": 20737,
      "deltaTime": 20737,
      "deltaDistance": 0,
      "points": 0,
      "arr": 1127,
      "rating": 1045,
      "pen": 3,
      "gender": "2",
      "ageBand": "",
      "ngb": "",
      "ngbID": "",
      "uciID": "",
      "playerId": "Bot4361",
      "country": "bel",
      "isDNF": false,
      "isBot": true,
      "avgHr": 169,
      "maxHr": 205
    },
    {
      "position": 19,
      "time": 2185651,
      "avgPower": 230,
      "maxPower": 1275,
      "nrmPower": 241,
      "firstName": "Gennaro",
      "lastName": "D'Angelo",
      "teamName": "eVOX",
      "distance": 23541109,
      "delta": 20913,
      "deltaTime": 20913,
      "deltaDistance": 0,
      "points": 0,
      "arr": 1014,
      "rating": 994,
      "pen": 3,
      "gender": "2",
      "ageBand": "",
      "ngb": "",
      "ngbID": "",
      "uciID": "",
      "playerId": "Bot6705",
      "country": "ita",
      "isDNF": false,
      "isBot": true,
      "avgHr": 161,
      "maxHr": 190
    },
    {
      "position": 20,
      "time": 2185792,
      "avgPower": 209,
      "maxPower": 1067,
      "nrmPower": 218,
      "firstName": "Yannick",
      "lastName": "Thiry",
      "teamName": "",
      "distance": 23541109,
      "delta": 21054,
      "deltaTime": 21054,
      "deltaDistance": 0,
      "points": 0,
      "arr": 787,
      "rating": 780,
      "pen": 3,
      "gender": "2",
      "ageBand": "",
      "ngb": "",
      "ngbID": "",
      "uciID": "",
      "playerId": "Bot1158",
      "country": "bel",
      "isDNF": false,
      "isBot": true,
      "avgHr": 169,
      "maxHr": 200
    },
    {
      "position": 21,
      "time": 2185915,
      "avgPower": 234,
      "maxPower": 980,
      "nrmPower": 244,
      "firstName": "Royce",
      "lastName": "Murphy",
      "teamName": "",
      "distance": 23541109,
      "delta": 21177,
      "deltaTime": 21177,
      "deltaDistance": 0,
      "points": 0,
      "arr": 810,
      "rating": 807,
      "pen": 3,
      "gender": "2",
      "ageBand": "",
      "ngb": "",
      "ngbID": "",
      "uciID": "",
      "playerId": "Bot8042",
      "country": "aus",
      "isDNF": false,
      "isBot": true,
      "avgHr": 158,
      "maxHr": 185
    },
    {
      "position": 22,
      "time": 2186279,
      "avgPower": 200,
      "maxPower": 1040,
      "nrmPower": 207,
      "firstName": "Elmer",
      "lastName": "Shah",
      "teamName": "Patriot",
      "distance": 23541109,
      "delta": 21540,
      "deltaTime": 21540,
      "deltaDistance": 0,
      "points": 0,
      "arr": 812,
      "rating": 806,
      "pen": 3,
      "gender": "2",
      "ageBand": "",
      "ngb": "",
      "ngbID": "",
      "uciID": "",
      "playerId": "Bot3908",
      "country": "rsa",
      "isDNF": false,
      "isBot": true,
      "avgHr": 176,
      "maxHr": 207
    },
    {
      "position": 23,
      "time": 2186343,
      "avgPower": 201,
      "maxPower": 1015,
      "nrmPower": 208,
      "firstName": "Irving",
      "lastName": "Ruiz",
      "teamName": "",
      "distance": 23541109,
      "delta": 21605,
      "deltaTime": 21605,
      "deltaDistance": 0,
      "points": 0,
      "arr": 826,
      "rating": 789,
      "pen": 3,
      "gender": "2",
      "ageBand": "",
      "ngb": "",
      "ngbID": "",
      "uciID": "",
      "playerId": "Bot552",
      "country": "sgp",
      "isDNF": false,
      "isBot": true,
      "avgHr": 170,
      "maxHr": 197
    },
    {
      "position": 24,
      "time": 2186670,
      "avgPower": 246,
      "maxPower": 663,
      "nrmPower": 253,
      "firstName": "Roberta",
      "lastName": "Ruggiero",
      "teamName": "",
      "distance": 23541109,
      "delta": 21932,
      "deltaTime": 21932,
      "deltaDistance": 0,
      "points": 0,
      "arr": 912,
      "rating": 915,
      "pen": 3,
      "gender": "2",
      "ageBand": "",
      "ngb": "",
      "ngbID": "",
      "uciID": "",
      "playerId": "Bot8580",
      "country": "ita",
      "isDNF": false,
      "isBot": true,
      "avgHr": 159,
      "maxHr": 179
    },
    {
      "position": 25,
      "time": 2186709,
      "avgPower": 197,
      "maxPower": 1040,
      "nrmPower": 201,
      "firstName": "Juliette",
      "lastName": "Laurent",
      "teamName": "",
      "distance": 23541109,
      "delta": 21971,
      "deltaTime": 21971,
      "deltaDistance": 0,
      "points": 0,
      "arr": 874,
      "rating": 853,
      "pen": 3,
      "gender": "2",
      "ageBand": "",
      "ngb": "",
      "ngbID": "",
      "uciID": "",
      "playerId": "Bot8484",
      "country": "bel",
      "isDNF": false,
      "isBot": true,
      "avgHr": 168,
      "maxHr": 197
    },
    {
      "position": 26,
      "time": 2187336,
      "avgPower": 243,
      "maxPower": 545,
      "nrmPower": 252,
      "firstName": "Vasil",
      "lastName": "Gnjatić",
      "teamName": "Ampex",
      "distance": 23541109,
      "delta": 22598,
      "deltaTime": 22598,
      "deltaDistance": 0,
      "points": 0,
      "arr": 659,
      "rating": 687,
      "pen": 3,
      "gender": "2",
      "ageBand": "",
      "ngb": "",
      "ngbID": "",
      "uciID": "",
      "playerId": "Bot9314",
      "country": "cro",
      "isDNF": false,
      "isBot": true,
      "avgHr": 139,
      "maxHr": 154
    },
    {
      "position": 27,
      "time": 2187774,
      "avgPower": 209,
      "maxPower": 351,
      "nrmPower": 214,
      "firstName": "Marthe",
      "lastName": "Lemoine",
      "teamName": "Krowen",
      "distance": 23541109,
      "delta": 23036,
      "deltaTime": 23036,
      "deltaDistance": 0,
      "points": 0,
      "arr": 936,
      "rating": 916,
      "pen": 3,
      "gender": "2",
      "ageBand": "",
      "ngb": "",
      "ngbID": "",
      "uciID": "",
      "playerId": "Bot3802",
      "country": "fra",
      "isDNF": false,
      "isBot": true,
      "avgHr": 149,
      "maxHr": 160
    },
    {
      "position": 28,
      "time": 2188959,
      "avgPower": 188,
      "maxPower": 284,
      "nrmPower": 193,
      "firstName": "Simone",
      "lastName": "Albrecht",
      "teamName": "",
      "distance": 23541109,
      "delta": 24220,
      "deltaTime": 24220,
      "deltaDistance": 0,
      "points": 0,
      "arr": 788,
      "rating": 787,
      "pen": 3,
      "gender": "2",
      "ageBand": "",
      "ngb": "",
      "ngbID": "",
      "uciID": "",
      "playerId": "Bot1250",
      "country": "ger",
      "isDNF": false,
      "isBot": true,
      "avgHr": 144,
      "maxHr": 152
    },
    {
      "position": 29,
      "time": 2189088,
      "avgPower": 248,
      "maxPower": 383,
      "nrmPower": 255,
      "firstName": "Elisa",
      "lastName": "D'Amico",
      "teamName": "",
      "distance": 23541109,
      "delta": 24350,
      "deltaTime": 24350,
      "deltaDistance": 0,
      "points": 0,
      "arr": 719,
      "rating": 760,
      "pen": 3,
      "gender": "2",
      "ageBand": "",
      "ngb": "",
      "ngbID": "",
      "uciID": "",
      "playerId": "Bot553",
      "country": "ita",
      "isDNF": false,
      "isBot": true,
      "avgHr": 147,
      "maxHr": 159
    },
    {
      "position": 30,
      "time": 2189393,
      "avgPower": 191,
      "maxPower": 448,
      "nrmPower": 195,
      "firstName": "Flora",
      "lastName": "Crane",
      "teamName": "Patriot",
      "distance": 23541109,
      "delta": 24655,
      "deltaTime": 24655,
      "deltaDistance": 0,
      "points": 0,
      "arr": 673,
      "rating": 667,
      "pen": 3,
      "gender": "2",
      "ageBand": "",
      "ngb": "",
      "ngbID": "",
      "uciID": "",
      "playerId": "Bot2608",
      "country": "aus",
      "isDNF": false,
      "isBot": true,
      "avgHr": 161,
      "maxHr": 171
    },
    {
      "position": 31,
      "time": 2189792,
      "avgPower": 201,
      "maxPower": 353,
      "nrmPower": 206,
      "firstName": "Karla",
      "lastName": "McClain",
      "teamName": "",
      "distance": 23541109,
      "delta": 25054,
      "deltaTime": 25054,
      "deltaDistance": 0,
      "points": 0,
      "arr": 651,
      "rating": 641,
      "pen": 3,
      "gender": "2",
      "ageBand": "",
      "ngb": "",
      "ngbID": "",
      "uciID": "",
      "playerId": "Bot5259",
      "country": "aus",
      "isDNF": false,
      "isBot": true,
      "avgHr": 201,
      "maxHr": 218
    },
    {
      "position": 32,
      "time": 2190150,
      "avgPower": 188,
      "maxPower": 291,
      "nrmPower": 192,
      "firstName": "Elsa",
      "lastName": "Macias",
      "teamName": "Orbit",
      "distance": 23541109,
      "delta": 25411,
      "deltaTime": 25411,
      "deltaDistance": 0,
      "points": 0,
      "arr": 812,
      "rating": 793,
      "pen": 3,
      "gender": "2",
      "ageBand": "",
      "ngb": "",
      "ngbID": "",
      "uciID": "",
      "playerId": "Bot4203",
      "country": "usa",
      "isDNF": false,
      "isBot": true,
      "avgHr": 190,
      "maxHr": 201
    },
    {
      "position": 33,
      "time": 2191540,
      "avgPower": 217,
      "maxPower": 509,
      "nrmPower": 219,
      "firstName": "Adam",
      "lastName": "Simon",
      "teamName": "",
      "distance": 23541109,
      "delta": 26802,
      "deltaTime": 26802,
      "deltaDistance": 0,
      "points": 0,
      "arr": 710,
      "rating": 710,
      "pen": 3,
      "gender": "2",
      "ageBand": "",
      "ngb": "",
      "ngbID": "",
      "uciID": "",
      "playerId": "Bot1074",
      "country": "bel",
      "isDNF": false,
      "isBot": true,
      "avgHr": 184,
      "maxHr": 199
    },
    {
      "position": 34,
      "time": 2191603,
      "avgPower": 220,
      "maxPower": 370,
      "nrmPower": 223,
      "firstName": "Megan",
      "lastName": "Clarke",
      "teamName": "",
      "distance": 23541109,
      "delta": 26865,
      "deltaTime": 26865,
      "deltaDistance": 0,
      "points": 0,
      "arr": 701,
      "rating": 702,
      "pen": 3,
      "gender": "2",
      "ageBand": "",
      "ngb": "",
      "ngbID": "",
      "uciID": "",
      "playerId": "Bot548",
      "country": "wal",
      "isDNF": false,
      "isBot": true,
      "avgHr": 174,
      "maxHr": 184
    },
    {
      "position": 35,
      "time": 2213368,
      "avgPower": 199,
      "maxPower": 1040,
      "nrmPower": 210,
      "firstName": "Rune",
      "lastName": "Van",
      "teamName": "Meisterkuhl",
      "distance": 23541109,
      "delta": 48630,
      "deltaTime": 48630,
      "deltaDistance": 0,
      "points": 0,
      "arr": 787,
      "rating": 772,
      "pen": 3,
      "gender": "2",
      "ageBand": "",
      "ngb": "",
      "ngbID": "",
      "uciID": "",
      "playerId": "Bot3322",
      "country": "bel",
      "isDNF": false,
      "isBot": true,
      "avgHr": 145,
      "maxHr": 177
    },
    {
      "position": 36,
      "time": 2213598,
      "avgPower": 249,
      "maxPower": 1101,
      "nrmPower": 260,
      "firstName": "Greg",
      "lastName": "George",
      "teamName": "",
      "distance": 23541109,
      "delta": 48860,
      "deltaTime": 48860,
      "deltaDistance": 0,
      "points": 0,
      "arr": 719,
      "rating": 736,
      "pen": 3,
      "gender": "2",
      "ageBand": "",
      "ngb": "",
      "ngbID": "",
      "uciID": "",
      "playerId": "Bot5048",
      "country": "usa",
      "isDNF": false,
      "isBot": true,
      "avgHr": 153,
      "maxHr": 184
    },
    {
      "position": 37,
      "time": 2213942,
      "avgPower": 177,
      "maxPower": 789,
      "nrmPower": 183,
      "firstName": "Alisa",
      "lastName": "Halonen",
      "teamName": "Zonkify",
      "distance": 23541109,
      "delta": 49204,
      "deltaTime": 49204,
      "deltaDistance": 0,
      "points": 0,
      "arr": 653,
      "rating": 639,
      "pen": 3,
      "gender": "2",
      "ageBand": "",
      "ngb": "",
      "ngbID": "",
      "uciID": "",
      "playerId": "Bot6309",
      "country": "fin",
      "isDNF": false,
      "isBot": true,
      "avgHr": 167,
      "maxHr": 192
    },
    {
      "position": 38,
      "time": 2479566,
      "avgPower": 174,
      "maxPower": 308,
      "nrmPower": 179,
      "firstName": "Alfredo",
      "lastName": "Gutierrez",
      "teamName": "",
      "distance": 23541109,
      "delta": 314828,
      "deltaTime": 314828,
      "deltaDistance": 0,
      "points": 0,
      "arr": 714,
      "rating": 675,
      "pen": 3,
      "gender": "2",
      "ageBand": "",
      "ngb": "",
      "ngbID": "",
      "uciID": "",
      "playerId": "Bot6851",
      "country": "cub",
      "isDNF": false,
      "isBot": true,
      "avgHr": 157,
      "maxHr": 167
    },
    {
      "position": 32767,
      "time": 2208399,
      "avgPower": 114,
      "maxPower": 139,
      "nrmPower": 116,
      "firstName": "Antone",
      "lastName": "McGuire",
      "teamName": "",
      "distance": 17778386,
      "delta": 0,
      "deltaTime": 0,
      "deltaDistance": 0,
      "points": 0,
      "arr": 749,
      "rating": 697,
      "pen": 3,
      "gender": "2",
      "ageBand": "",
      "ngb": "",
      "ngbID": "",
      "uciID": "",
      "playerId": "Bot348",
      "country": "usa",
      "isDNF": true,
      "isBot": true,
      "avgHr": 160,
      "maxHr": 167
    }
  ]
}