{
  "metadata": {
    "eventKey": 95947,
    "pen": 1,
    "careerEventId": 7,
    "scheduleKey": 55428,
    "eventName": "Flat Eight Criterium - TPV Career Mode",
    "completedAt": "2026-01-06T13:45:00.589Z",
    "raceDate": "2026-01-06T13:45:00.589Z",
    "fetchedAt": "2026-01-06T13:50:17.406Z",
    "source": "api"
  },
  "results": [
    {
      "position": 1,
      "time": 2127949,
      "avgPower": 261,
      "maxPower": 815,
      "nrmPower": 283,
      "firstName": "Ryan",
      "lastName": "Yates",
      "teamName": "Allkin Racing",
      "distance": 25674125,
      "delta": 0,
      "deltaTime": 0,
      "deltaDistance": 0,
      "points": 0,
      "arr": 1278,
      "rating": 1318,
      "pen": 1,
      "gender": "0",
      "ageBand": "40-44",
      "ngb": "",
      "ngbID": "",
      "uciID": "",
      "playerId": "2FDBB5DD4345DCB5",
      "country": "usa",
      "isDNF": false,
      "isBot": false,
      "avgHr": 145,
      "maxHr": 173
    },
    {
      "position": 2,
      "time": 2128268,
      "avgPower": 308,
      "maxPower": 472,
      "nrmPower": 316,
      "firstName": "David",
      "lastName": "Prakash",
      "teamName": "",
      "distance": 25674125,
      "delta": 319,
      "deltaTime": 319,
      "deltaDistance": 0,
      "points": 0,
      "arr": 1277,
      "rating": 1289,
      "pen": 1,
      "gender": "2",
      "ageBand": "",
      "ngb": "",
      "ngbID": "",
      "uciID": "",
      "playerId": "Bot4986",
      "country": "fij",
      "isDNF": false,
      "isBot": true,
      "avgHr": 149,
      "maxHr": 155
    },
    {
      "position": 3,
      "time": 2145049,
      "avgPower": 351,
      "maxPower": 669,
      "nrmPower": 361,
      "firstName": "Vicente",
      "lastName": "Chung",
      "teamName": "",
      "distance": 25674125,
      "delta": 17099,
      "deltaTime": 17099,
      "deltaDistance": 0,
      "points": 0,
      "arr": 1264,
      "rating": 1326,
      "pen": 1,
      "gender": "2",
      "ageBand": "",
      "ngb": "",
      "ngbID": "",
      "uciID": "",
      "playerId": "Bot8976",
      "country": "eng",
      "isDNF": false,
      "isBot": true,
      "avgHr": 155,
      "maxHr": 167
    },
    {
      "position": 4,
      "time": 2159273,
      "avgPower": 306,
      "maxPower": 1002,
      "nrmPower": 311,
      "firstName": "Jérôme",
      "lastName": "Renard",
      "teamName": "",
      "distance": 25674125,
      "delta": 31323,
      "deltaTime": 31323,
      "deltaDistance": 0,
      "points": 0,
      "arr": 1022,
      "rating": 1054,
      "pen": 1,
      "gender": "2",
      "ageBand": "",
      "ngb": "",
      "ngbID": "",
      "uciID": "",
      "playerId": "Bot4348",
      "country": "fra",
      "isDNF": false,
      "isBot": true,
      "avgHr": 168,
      "maxHr": 190
    },
    {
      "position": 5,
      "time": 2159375,
      "avgPower": 343,
      "maxPower": 1022,
      "nrmPower": 349,
      "firstName": "Erwin",
      "lastName": "Dougherty",
      "teamName": "",
      "distance": 25674125,
      "delta": 31425,
      "deltaTime": 31425,
      "deltaDistance": 0,
      "points": 0,
      "arr": 1207,
      "rating": 1256,
      "pen": 1,
      "gender": "2",
      "ageBand": "",
      "ngb": "",
      "ngbID": "",
      "uciID": "",
      "playerId": "Bot4582",
      "country": "aus",
      "isDNF": false,
      "isBot": true,
      "avgHr": 154,
      "maxHr": 172
    },
    {
      "position": 6,
      "time": 2159495,
      "avgPower": 301,
      "maxPower": 524,
      "nrmPower": 305,
      "firstName": "Tapio",
      "lastName": "Salminen",
      "teamName": "Meisterkuhl",
      "distance": 25674125,
      "delta": 31545,
      "deltaTime": 31545,
      "deltaDistance": 0,
      "points": 0,
      "arr": 1217,
      "rating": 1228,
      "pen": 1,
      "gender": "2",
      "ageBand": "",
      "ngb": "",
      "ngbID": "",
      "uciID": "",
      "playerId": "Bot322",
      "country": "fin",
      "isDNF": false,
      "isBot": true,
      "avgHr": 172,
      "maxHr": 180
    },
    {
      "position": 7,
      "time": 2163536,
      "avgPower": 284,
      "maxPower": 448,
      "nrmPower": 291,
      "firstName": "Ashraf",
      "lastName": "Ramadan",
      "teamName": "",
      "distance": 25674125,
      "delta": 35587,
      "deltaTime": 35587,
      "deltaDistance": 0,
      "points": 0,
      "arr": 1204,
      "rating": 1200,
      "pen": 1,
      "gender": "2",
      "ageBand": "",
      "ngb": "",
      "ngbID": "",
      "uciID": "",
      "playerId": "Bot4767",
      "country": "egy",
      "isDNF": false,
      "isBot": true,
      "avgHr": 176,
      "maxHr": 186
    },
    {
      "position": 8,
      "time": 2163544,
      "avgPower": 311,
      "maxPower": 464,
      "nrmPower": 315,
      "firstName": "Lachlan",
      "lastName": "Crawford",
      "teamName": "",
      "distance": 25674125,
      "delta": 35594,
      "deltaTime": 35594,
      "deltaDistance": 0,
      "points": 0,
      "arr": 1017,
      "rating": 1035,
      "pen": 1,
      "gender": "2",
      "ageBand": "",
      "ngb": "",
      "ngbID": "",
      "uciID": "",
      "playerId": "Bot6593",
      "country": "sco",
      "isDNF": false,
      "isBot": true,
      "avgHr": 153,
      "maxHr": 159
    },
    {
      "position": 9,
      "time": 2163618,
      "avgPower": 275,
      "maxPower": 411,
      "nrmPower": 279,
      "firstName": "Christopher",
      "lastName": "Diaz",
      "teamName": "Douvan",
      "distance": 25674125,
      "delta": 35669,
      "deltaTime": 35669,
      "deltaDistance": 0,
      "points": 0,
      "arr": 1020,
      "rating": 1026,
      "pen": 1,
      "gender": "2",
      "ageBand": "",
      "ngb": "",
      "ngbID": "",
      "uciID": "",
      "playerId": "Bot3536",
      "country": "aus",
      "isDNF": false,
      "isBot": true,
      "avgHr": 174,
      "maxHr": 180
    },
    {
      "position": 10,
      "time": 2163673,
      "avgPower": 268,
      "maxPower": 479,
      "nrmPower": 275,
      "firstName": "Cristian",
      "lastName": "Castaño",
      "teamName": "",
      "distance": 25674125,
      "delta": 35723,
      "deltaTime": 35723,
      "deltaDistance": 0,
      "points": 0,
      "arr": 1164,
      "rating": 1156,
      "pen": 1,
      "gender": "2",
      "ageBand": "",
      "ngb": "",
      "ngbID": "",
      "uciID": "",
      "playerId": "Bot3374",
      "country": "col",
      "isDNF": false,
      "isBot": true,
      "avgHr": 191,
      "maxHr": 203
    },
    {
      "position": 11,
      "time": 2163738,
      "avgPower": 292,
      "maxPower": 443,
      "nrmPower": 298,
      "firstName": "Willy",
      "lastName": "Atkins",
      "teamName": "",
      "distance": 25674125,
      "delta": 35788,
      "deltaTime": 35788,
      "deltaDistance": 0,
      "points": 0,
      "arr": 1050,
      "rating": 1058,
      "pen": 1,
      "gender": "2",
      "ageBand": "",
      "ngb": "",
      "ngbID": "",
      "uciID": "",
      "playerId": "Bot8846",
      "country": "nzl",
      "isDNF": false,
      "isBot": true,
      "avgHr": 182,
      "maxHr": 190
    },
    {
      "position": 12,
      "time": 2170301,
      "avgPower": 292,
      "maxPower": 999,
      "nrmPower": 297,
      "firstName": "Antonio",
      "lastName": "Lima",
      "teamName": "",
      "distance": 25674125,
      "delta": 42351,
      "deltaTime": 42351,
      "deltaDistance": 0,
      "points": 0,
      "arr": 1084,
      "rating": 1103,
      "pen": 1,
      "gender": "2",
      "ageBand": "",
      "ngb": "",
      "ngbID": "",
      "uciID": "",
      "playerId": "Bot8187",
      "country": "bra",
      "isDNF": false,
      "isBot": true,
      "avgHr": 164,
      "maxHr": 178
    },
    {
      "position": 13,
      "time": 2173001,
      "avgPower": 270,
      "maxPower": 1204,
      "nrmPower": 277,
      "firstName": "Bart",
      "lastName": "Vermeulen",
      "teamName": "",
      "distance": 25674125,
      "delta": 45052,
      "deltaTime": 45052,
      "deltaDistance": 0,
      "points": 0,
      "arr": 1127,
      "rating": 1107,
      "pen": 1,
      "gender": "2",
      "ageBand": "",
      "ngb": "",
      "ngbID": "",
      "uciID": "",
      "playerId": "Bot7997",
      "country": "ned",
      "isDNF": false,
      "isBot": true,
      "avgHr": 149,
      "maxHr": 176
    },
    {
      "position": 14,
      "time": 2173005,
      "avgPower": 277,
      "maxPower": 1017,
      "nrmPower": 283,
      "firstName": "Curt",
      "lastName": "McCullough",
      "teamName": "Heat",
      "distance": 25674125,
      "delta": 45055,
      "deltaTime": 45055,
      "deltaDistance": 0,
      "points": 0,
      "arr": 1205,
      "rating": 1239,
      "pen": 1,
      "gender": "2",
      "ageBand": "",
      "ngb": "",
      "ngbID": "",
      "uciID": "",
      "playerId": "Bot1707",
      "country": "aus",
      "isDNF": false,
      "isBot": true,
      "avgHr": 151,
      "maxHr": 174
    },
    {
      "position": 15,
      "time": 2173025,
      "avgPower": 250,
      "maxPower": 1179,
      "nrmPower": 256,
      "firstName": "Joon",
      "lastName": "Cheon",
      "teamName": "Hector",
      "distance": 25674125,
      "delta": 45075,
      "deltaTime": 45075,
      "deltaDistance": 0,
      "points": 0,
      "arr": 1120,
      "rating": 1100,
      "pen": 1,
      "gender": "2",
      "ageBand": "",
      "ngb": "",
      "ngbID": "",
      "uciID": "",
      "playerId": "Bot1926",
      "country": "kor",
      "isDNF": false,
      "isBot": true,
      "avgHr": 167,
      "maxHr": 197
    },
    {
      "position": 16,
      "time": 2173063,
      "avgPower": 245,
      "maxPower": 1300,
      "nrmPower": 251,
      "firstName": "Martin",
      "lastName": "Mehmed",
      "teamName": "Sherpa",
      "distance": 25674125,
      "delta": 45113,
      "deltaTime": 45113,
      "deltaDistance": 0,
      "points": 0,
      "arr": 1033,
      "rating": 1020,
      "pen": 1,
      "gender": "2",
      "ageBand": "",
      "ngb": "",
      "ngbID": "",
      "uciID": "",
      "playerId": "Bot4420",
      "country": "bul",
      "isDNF": false,
      "isBot": true,
      "avgHr": 190,
      "maxHr": 230
    },
    {
      "position": 17,
      "time": 2173066,
      "avgPower": 293,
      "maxPower": 1424,
      "nrmPower": 301,
      "firstName": "James",
      "lastName": "Roche",
      "teamName": "",
      "distance": 25674125,
      "delta": 45116,
      "deltaTime": 45116,
      "deltaDistance": 0,
      "points": 0,
      "arr": 1182,
      "rating": 1184,
      "pen": 1,
      "gender": "2",
      "ageBand": "",
      "ngb": "",
      "ngbID": "",
      "uciID": "",
      "playerId": "Bot2568",
      "country": "irl",
      "isDNF": false,
      "isBot": true,
      "avgHr": 183,
      "maxHr": 221
    },
    {
      "position": 18,
      "time": 2173101,
      "avgPower": 257,
      "maxPower": 1159,
      "nrmPower": 262,
      "firstName": "Igor",
      "lastName": "Mraz",
      "teamName": "",
      "distance": 25674125,
      "delta": 45151,
      "deltaTime": 45151,
      "deltaDistance": 0,
      "points": 0,
      "arr": 1080,
      "rating": 1062,
      "pen": 1,
      "gender": "2",
      "ageBand": "",
      "ngb": "",
      "ngbID": "",
      "uciID": "",
      "playerId": "Bot6281",
      "country": "cro",
      "isDNF": false,
      "isBot": true,
      "avgHr": 189,
      "maxHr": 223
    },
    {
      "position": 19,
      "time": 2173117,
      "avgPower": 285,
      "maxPower": 934,
      "nrmPower": 292,
      "firstName": "Marshall",
      "lastName": "Tucker",
      "teamName": "Hinal",
      "distance": 25674125,
      "delta": 45167,
      "deltaTime": 45167,
      "deltaDistance": 0,
      "points": 0,
      "arr": 1194,
      "rating": 1215,
      "pen": 1,
      "gender": "2",
      "ageBand": "",
      "ngb": "",
      "ngbID": "",
      "uciID": "",
      "playerId": "Bot6831",
      "country": "aus",
      "isDNF": false,
      "isBot": true,
      "avgHr": 166,
      "maxHr": 189
    },
    {
      "position": 20,
      "time": 2173217,
      "avgPower": 292,
      "maxPower": 1416,
      "nrmPower": 300,
      "firstName": "Judson",
      "lastName": "Erickson",
      "teamName": "",
      "distance": 25674125,
      "delta": 45267,
      "deltaTime": 45267,
      "deltaDistance": 0,
      "points": 0,
      "arr": 1054,
      "rating": 1064,
      "pen": 1,
      "gender": "2",
      "ageBand": "",
      "ngb": "",
      "ngbID": "",
      "uciID": "",
      "playerId": "Bot8991",
      "country": "rsa",
      "isDNF": false,
      "isBot": true,
      "avgHr": 158,
      "maxHr": 187
    },
    {
      "position": 21,
      "time": 2173246,
      "avgPower": 281,
      "maxPower": 773,
      "nrmPower": 290,
      "firstName": "Arthur",
      "lastName": "Clercq",
      "teamName": "",
      "distance": 25674125,
      "delta": 45296,
      "deltaTime": 45296,
      "deltaDistance": 0,
      "points": 0,
      "arr": 1100,
      "rating": 1114,
      "pen": 1,
      "gender": "2",
      "ageBand": "",
      "ngb": "",
      "ngbID": "",
      "uciID": "",
      "playerId": "Bot3690",
      "country": "bel",
      "isDNF": false,
      "isBot": true,
      "avgHr": 186,
      "maxHr": 207
    },
    {
      "position": 22,
      "time": 2173473,
      "avgPower": 260,
      "maxPower": 1310,
      "nrmPower": 267,
      "firstName": "Nicolas",
      "lastName": "Jung",
      "teamName": "",
      "distance": 25674125,
      "delta": 45523,
      "deltaTime": 45523,
      "deltaDistance": 0,
      "points": 0,
      "arr": 1147,
      "rating": 1128,
      "pen": 1,
      "gender": "2",
      "ageBand": "",
      "ngb": "",
      "ngbID": "",
      "uciID": "",
      "playerId": "Bot9875",
      "country": "lux",
      "isDNF": false,
      "isBot": true,
      "avgHr": 170,
      "maxHr": 202
    },
    {
      "position": 23,
      "time": 2173569,
      "avgPower": 257,
      "maxPower": 905,
      "nrmPower": 262,
      "firstName": "Thad",
      "lastName": "Franklin",
      "teamName": "",
      "distance": 25674125,
      "delta": 45619,
      "deltaTime": 45619,
      "deltaDistance": 0,
      "points": 0,
      "arr": 1234,
      "rating": 1210,
      "pen": 1,
      "gender": "2",
      "ageBand": "",
      "ngb": "",
      "ngbID": "",
      "uciID": "",
      "playerId": "Bot5574",
      "country": "usa",
      "isDNF": false,
      "isBot": true,
      "avgHr": 147,
      "maxHr": 168
    },
    {
      "position": 24,
      "time": 2173767,
      "avgPower": 225,
      "maxPower": 1190,
      "nrmPower": 229,
      "firstName": "Jacob",
      "lastName": "Andersen",
      "teamName": "YES",
      "distance": 25674125,
      "delta": 45817,
      "deltaTime": 45817,
      "deltaDistance": 0,
      "points": 0,
      "arr": 1036,
      "rating": 1030,
      "pen": 1,
      "gender": "2",
      "ageBand": "",
      "ngb": "",
      "ngbID": "",
      "uciID": "",
      "playerId": "Bot8135",
      "country": "den",
      "isDNF": false,
      "isBot": true,
      "avgHr": 191,
      "maxHr": 233
    },
    {
      "position": 25,
      "time": 2173885,
      "avgPower": 280,
      "maxPower": 423,
      "nrmPower": 285,
      "firstName": "Shivansh",
      "lastName": "Khanna",
      "teamName": "Formix",
      "distance": 25674125,
      "delta": 45935,
      "deltaTime": 45935,
      "deltaDistance": 0,
      "points": 0,
      "arr": 1061,
      "rating": 1082,
      "pen": 1,
      "gender": "2",
      "ageBand": "",
      "ngb": "",
      "ngbID": "",
      "uciID": "",
      "playerId": "Bot417",
      "country": "ind",
      "isDNF": false,
      "isBot": true,
      "avgHr": 161,
      "maxHr": 168
    },
    {
      "position": 26,
      "time": 2173987,
      "avgPower": 356,
      "maxPower": 1975,
      "nrmPower": 364,
      "firstName": "Théo",
      "lastName": "Roy",
      "teamName": "",
      "distance": 25674125,
      "delta": 46037,
      "deltaTime": 46037,
      "deltaDistance": 0,
      "points": 0,
      "arr": 1101,
      "rating": 1162,
      "pen": 1,
      "gender": "2",
      "ageBand": "",
      "ngb": "",
      "ngbID": "",
      "uciID": "",
      "playerId": "Bot4058",
      "country": "fra",
      "isDNF": false,
      "isBot": true,
      "avgHr": 165,
      "maxHr": 189
    },
    {
      "position": 27,
      "time": 2174095,
      "avgPower": 270,
      "maxPower": 1410,
      "nrmPower": 276,
      "firstName": "Ronald",
      "lastName": "De Boer",
      "teamName": "",
      "distance": 25674125,
      "delta": 46145,
      "deltaTime": 46145,
      "deltaDistance": 0,
      "points": 0,
      "arr": 1140,
      "rating": 1164,
      "pen": 1,
      "gender": "2",
      "ageBand": "",
      "ngb": "",
      "ngbID": "",
      "uciID": "",
      "playerId": "Bot4983",
      "country": "ned",
      "isDNF": false,
      "isBot": true,
      "avgHr": 168,
      "maxHr": 198
    },
    {
      "position": 28,
      "time": 2174391,
      "avgPower": 264,
      "maxPower": 946,
      "nrmPower": 269,
      "firstName": "Ariel",
      "lastName": "Jabarin",
      "teamName": "",
      "distance": 25674125,
      "delta": 46441,
      "deltaTime": 46441,
      "deltaDistance": 0,
      "points": 0,
      "arr": 1175,
      "rating": 1174,
      "pen": 1,
      "gender": "2",
      "ageBand": "",
      "ngb": "",
      "ngbID": "",
      "uciID": "",
      "playerId": "Bot2451",
      "country": "isr",
      "isDNF": false,
      "isBot": true,
      "avgHr": 161,
      "maxHr": 181
    },
    {
      "position": 29,
      "time": 2175601,
      "avgPower": 227,
      "maxPower": 957,
      "nrmPower": 231,
      "firstName": "Yosyp",
      "lastName": "Melnichuk",
      "teamName": "",
      "distance": 25674125,
      "delta": 47651,
      "deltaTime": 47651,
      "deltaDistance": 0,
      "points": 0,
      "arr": 1180,
      "rating": 1128,
      "pen": 1,
      "gender": "2",
      "ageBand": "",
      "ngb": "",
      "ngbID": "",
      "uciID": "",
      "playerId": "Bot2559",
      "country": "ukr",
      "isDNF": false,
      "isBot": true,
      "avgHr": 179,
      "maxHr": 203
    },
    {
      "position": 30,
      "time": 2175607,
      "avgPower": 241,
      "maxPower": 1115,
      "nrmPower": 244,
      "firstName": "Olli",
      "lastName": "Vainio",
      "teamName": "YES",
      "distance": 25674125,
      "delta": 47657,
      "deltaTime": 47657,
      "deltaDistance": 0,
      "points": 0,
      "arr": 1198,
      "rating": 1155,
      "pen": 1,
      "gender": "2",
      "ageBand": "",
      "ngb": "",
      "ngbID": "",
      "uciID": "",
      "playerId": "Bot8835",
      "country": "fin",
      "isDNF": false,
      "isBot": true,
      "avgHr": 171,
      "maxHr": 195
    },
    {
      "position": 31,
      "time": 2176310,
      "avgPower": 254,
      "maxPower": 460,
      "nrmPower": 264,
      "firstName": "Chen",
      "lastName": "Leung",
      "teamName": "Optech",
      "distance": 25674125,
      "delta": 48360,
      "deltaTime": 48360,
      "deltaDistance": 0,
      "points": 0,
      "arr": 1109,
      "rating": 1105,
      "pen": 1,
      "gender": "2",
      "ageBand": "",
      "ngb": "",
      "ngbID": "",
      "uciID": "",
      "playerId": "Bot1618",
      "country": "hkg",
      "isDNF": false,
      "isBot": true,
      "avgHr": 157,
      "maxHr": 166
    },
    {
      "position": 32,
      "time": 2176377,
      "avgPower": 263,
      "maxPower": 476,
      "nrmPower": 271,
      "firstName": "Vladimir",
      "lastName": "Rockova",
      "teamName": "Aspire",
      "distance": 25674125,
      "delta": 48427,
      "deltaTime": 48427,
      "deltaDistance": 0,
      "points": 0,
      "arr": 1136,
      "rating": 1125,
      "pen": 1,
      "gender": "2",
      "ageBand": "",
      "ngb": "",
      "ngbID": "",
      "uciID": "",
      "playerId": "Bot2329",
      "country": "slo",
      "isDNF": false,
      "isBot": true,
      "avgHr": 187,
      "maxHr": 199
    },
    {
      "position": 33,
      "time": 2176681,
      "avgPower": 286,
      "maxPower": 535,
      "nrmPower": 296,
      "firstName": "Michael",
      "lastName": "Brandt",
      "teamName": "",
      "distance": 25674125,
      "delta": 48731,
      "deltaTime": 48731,
      "deltaDistance": 0,
      "points": 0,
      "arr": 1043,
      "rating": 1056,
      "pen": 1,
      "gender": "2",
      "ageBand": "",
      "ngb": "",
      "ngbID": "",
      "uciID": "",
      "playerId": "Bot745",
      "country": "ger",
      "isDNF": false,
      "isBot": true,
      "avgHr": 188,
      "maxHr": 202
    },
    {
      "position": 34,
      "time": 2176690,
      "avgPower": 278,
      "maxPower": 651,
      "nrmPower": 286,
      "firstName": "Shelton",
      "lastName": "Montes",
      "teamName": "Fujikai",
      "distance": 25674125,
      "delta": 48740,
      "deltaTime": 48740,
      "deltaDistance": 0,
      "points": 0,
      "arr": 1102,
      "rating": 1105,
      "pen": 1,
      "gender": "2",
      "ageBand": "",
      "ngb": "",
      "ngbID": "",
      "uciID": "",
      "playerId": "Bot2113",
      "country": "usa",
      "isDNF": false,
      "isBot": true,
      "avgHr": 176,
      "maxHr": 188
    },
    {
      "position": 35,
      "time": 2176762,
      "avgPower": 275,
      "maxPower": 501,
      "nrmPower": 283,
      "firstName": "Thiago",
      "lastName": "Soares",
      "teamName": "",
      "distance": 25674125,
      "delta": 48813,
      "deltaTime": 48813,
      "deltaDistance": 0,
      "points": 0,
      "arr": 1073,
      "rating": 1079,
      "pen": 1,
      "gender": "2",
      "ageBand": "",
      "ngb": "",
      "ngbID": "",
      "uciID": "",
      "playerId": "Bot1062",
      "country": "bra",
      "isDNF": false,
      "isBot": true,
      "avgHr": 163,
      "maxHr": 173
    },
    {
      "position": 36,
      "time": 2177198,
      "avgPower": 277,
      "maxPower": 502,
      "nrmPower": 284,
      "firstName": "Dorthy",
      "lastName": "Schmitt",
      "teamName": "",
      "distance": 25674125,
      "delta": 49248,
      "deltaTime": 49248,
      "deltaDistance": 0,
      "points": 0,
      "arr": 1059,
      "rating": 1060,
      "pen": 1,
      "gender": "2",
      "ageBand": "",
      "ngb": "",
      "ngbID": "",
      "uciID": "",
      "playerId": "Bot7577",
      "country": "rsa",
      "isDNF": false,
      "isBot": true,
      "avgHr": 185,
      "maxHr": 197
    },
    {
      "position": 37,
      "time": 2177303,
      "avgPower": 260,
      "maxPower": 386,
      "nrmPower": 263,
      "firstName": "Bas",
      "lastName": "Van der Veen",
      "teamName": "Kumori",
      "distance": 25674125,
      "delta": 49353,
      "deltaTime": 49353,
      "deltaDistance": 0,
      "points": 0,
      "arr": 1106,
      "rating": 1093,
      "pen": 1,
      "gender": "2",
      "ageBand": "",
      "ngb": "",
      "ngbID": "",
      "uciID": "",
      "playerId": "Bot3440",
      "country": "ned",
      "isDNF": false,
      "isBot": true,
      "avgHr": 172,
      "maxHr": 178
    },
    {
      "position": 38,
      "time": 2177518,
      "avgPower": 222,
      "maxPower": 388,
      "nrmPower": 228,
      "firstName": "Edward",
      "lastName": "James",
      "teamName": "Formix",
      "distance": 25674125,
      "delta": 49568,
      "deltaTime": 49568,
      "deltaDistance": 0,
      "points": 0,
      "arr": 1121,
      "rating": 1054,
      "pen": 1,
      "gender": "2",
      "ageBand": "",
      "ngb": "",
      "ngbID": "",
      "uciID": "",
      "playerId": "Bot9517",
      "country": "can",
      "isDNF": false,
      "isBot": true,
      "avgHr": 168,
      "maxHr": 177
    },
    {
      "position": 39,
      "time": 2179855,
      "avgPower": 224,
      "maxPower": 328,
      "nrmPower": 225,
      "firstName": "Annie",
      "lastName": "David",
      "teamName": "AI Thunder",
      "distance": 25674125,
      "delta": 51906,
      "deltaTime": 51906,
      "deltaDistance": 0,
      "points": 0,
      "arr": 1031,
      "rating": 1023,
      "pen": 1,
      "gender": "2",
      "ageBand": "",
      "ngb": "",
      "ngbID": "",
      "uciID": "",
      "playerId": "Bot9100",
      "country": "fra",
      "isDNF": false,
      "isBot": true,
      "avgHr": 164,
      "maxHr": 171
    }
  ]
}